{"levelName":"Level_0001_112.json","handPokerCount":17,"pokerInfo":[{"fPosX":-221.0,"fPosY":219.0,"fRotation":0.0,"nGroupID":1},{"fPosX":-362.0,"fPosY":221.0,"fRotation":0.0,"nGroupID":1},{"fPosX":-503.0,"fPosY":290.0,"fRotation":0.0,"nGroupID":1},{"fPosX":202.0,"fPosY":217.0,"fRotation":0.0,"nGroupID":1},{"fPosX":343.0,"fPosY":219.0,"fRotation":0.0,"nGroupID":1},{"fPosX":484.0,"fPosY":290.0,"fRotation":0.0,"nGroupID":1},{"fPosX":-150.0,"fPosY":108.0,"fRotation":0.0,"nGroupID":1},{"fPosX":131.0,"fPosY":108.0,"fRotation":0.0,"nGroupID":1},{"fPosX":413.0,"fPosY":108.0,"fRotation":0.0,"nGroupID":1},{"fPosX":-432.0,"fPosY":108.0,"fRotation":0.0,"nGroupID":1},{"fPosX":-80.0,"fPosY":290.0,"fRotation":0.0,"nGroupID":1},{"fPosX":61.0,"fPosY":290.0,"fRotation":0.0,"nGroupID":1},{"fPosX":61.0,"fPosY":69.0,"fRotation":0.0,"nGroupID":1},{"fPosX":-80.0,"fPosY":69.0,"fRotation":0.0,"nGroupID":1},{"fPosX":-177.0,"fPosY":-45.0,"fRotation":0.0,"nGroupID":2},{"fPosX":157.0,"fPosY":-45.0,"fRotation":0.0,"nGroupID":2},{"fPosX":-407.0,"fPosY":-45.0,"fRotation":0.0,"nGroupID":2},{"fPosX":388.0,"fPosY":-45.0,"fRotation":0.0,"nGroupID":2},{"fPosX":202.0,"fPosY":60.0,"fRotation":0.0,"nGroupID":2},{"fPosX":343.0,"fPosY":60.0,"fRotation":0.0,"nGroupID":2},{"fPosX":484.0,"fPosY":69.0,"fRotation":0.0,"nGroupID":2},{"fPosX":-503.0,"fPosY":69.0,"fRotation":0.0,"nGroupID":2},{"fPosX":-362.0,"fPosY":60.0,"fRotation":0.0,"nGroupID":2},{"fPosX":-221.0,"fPosY":60.0,"fRotation":0.0,"nGroupID":2},{"fPosX":-10.0,"fPosY":180.0,"fRotation":0.0,"nGroupID":1},{"fPosX":554.0,"fPosY":180.0,"fRotation":0.0,"nGroupID":2},{"fPosX":-573.0,"fPosY":180.0,"fRotation":0.0,"nGroupID":2},{"fPosX":-291.0,"fPosY":170.0,"fRotation":0.0,"nGroupID":2},{"fPosX":272.0,"fPosY":170.0,"fRotation":0.0,"nGroupID":2}],"LockAreaCount":0,"lockAreas":[],"unlockAreaCount":0,"unlockAreas":[],"lockGroup":{"nLockGroupCount":0,"lockGroups":[]}}